distance_locker/__init__.py
distance_locker/__main__.py
distance_locker-0.0.2.data/data/bin/bluetooth_distance_sensor.sh
distance_locker-0.0.2.dist-info/METADATA
distance_locker-0.0.2.dist-info/RECORD
distance_locker-0.0.2.dist-info/WHEEL
distance_locker-0.0.2.dist-info/entry_points.txt
distance_locker-0.0.2.dist-info/top_level.txt
