Metadata-Version: 2.1
Name: distance-locker
Version: 0.0.2
Summary: UNKNOWN
Home-page: https://github.com/liormizr/linux_distance_locker
Author: Lior Mizrahi
Author-email: li.mizr@gmail.com
License: UNKNOWN
Platform: UNKNOWN
